mrf_murl/__init__.py
mrf_murl/urlende.py
mrf_murl/urlsec.py
mrf_murl/data/public_suffix_list.dat
mrf_murl-0.1.2.dist-info/LICENSE.txt
mrf_murl-0.1.2.dist-info/METADATA
mrf_murl-0.1.2.dist-info/WHEEL
mrf_murl-0.1.2.dist-info/top_level.txt
mrf_murl-0.1.2.dist-info/RECORD
