Metadata-Version: 2.1
Name: mrf-murl
Version: 0.1.2
Summary: A URI manipulation tool aimed at web use.
Home-page: https://github.com/mariamrf/murl
Author: Mariam Maarouf
Author-email: mrf.mariam@gmail.com
License: UNKNOWN
Download-URL: https://github.com/mariamrf/murl/tarball/0.1.1
Keywords: uri,web
Platform: UNKNOWN
Classifier: Development Status :: 3 - Alpha
Classifier: Intended Audience :: Developers
Classifier: Topic :: Software Development :: Libraries :: Python Modules
Classifier: License :: OSI Approved :: MIT License
Classifier: Programming Language :: Python :: 3
